bin/libphasic.dll
bin/libphasiccpp.dll
include/eigen3/Eigen/Cholesky
include/eigen3/Eigen/CholmodSupport
include/eigen3/Eigen/Core
include/eigen3/Eigen/Dense
include/eigen3/Eigen/Eigen
include/eigen3/Eigen/Eigenvalues
include/eigen3/Eigen/Geometry
include/eigen3/Eigen/Householder
include/eigen3/Eigen/IterativeLinearSolvers
include/eigen3/Eigen/Jacobi
include/eigen3/Eigen/KLUSupport
include/eigen3/Eigen/LU
include/eigen3/Eigen/MetisSupport
include/eigen3/Eigen/OrderingMethods
include/eigen3/Eigen/PardisoSupport
include/eigen3/Eigen/PaStiXSupport
include/eigen3/Eigen/QR
include/eigen3/Eigen/QtAlignedMalloc
include/eigen3/Eigen/Sparse
include/eigen3/Eigen/SparseCholesky
include/eigen3/Eigen/SparseCore
include/eigen3/Eigen/SparseLU
include/eigen3/Eigen/SparseQR
include/eigen3/Eigen/SPQRSupport
include/eigen3/Eigen/src/Cholesky/LDLT.h
include/eigen3/Eigen/src/Cholesky/LLT.h
include/eigen3/Eigen/src/Cholesky/LLT_LAPACKE.h
include/eigen3/Eigen/src/CholmodSupport/CholmodSupport.h
include/eigen3/Eigen/src/Core/arch/AltiVec/Complex.h
include/eigen3/Eigen/src/Core/arch/AltiVec/MathFunctions.h
include/eigen3/Eigen/src/Core/arch/AltiVec/MatrixProduct.h
include/eigen3/Eigen/src/Core/arch/AltiVec/MatrixProductCommon.h
include/eigen3/Eigen/src/Core/arch/AltiVec/MatrixProductMMA.h
include/eigen3/Eigen/src/Core/arch/AltiVec/PacketMath.h
include/eigen3/Eigen/src/Core/arch/AVX/Complex.h
include/eigen3/Eigen/src/Core/arch/AVX/MathFunctions.h
include/eigen3/Eigen/src/Core/arch/AVX/PacketMath.h
include/eigen3/Eigen/src/Core/arch/AVX/TypeCasting.h
include/eigen3/Eigen/src/Core/arch/AVX512/Complex.h
include/eigen3/Eigen/src/Core/arch/AVX512/MathFunctions.h
include/eigen3/Eigen/src/Core/arch/AVX512/PacketMath.h
include/eigen3/Eigen/src/Core/arch/AVX512/TypeCasting.h
include/eigen3/Eigen/src/Core/arch/CUDA/Complex.h
include/eigen3/Eigen/src/Core/arch/Default/BFloat16.h
include/eigen3/Eigen/src/Core/arch/Default/ConjHelper.h
phasic-0.22.22.dist-info/METADATA
phasic-0.22.22.dist-info/WHEEL
phasic-0.22.22.dist-info/licenses/LICENSE
phasic-0.22.22.dist-info/licenses/LICENSE.txt
phasic-0.22.22.dist-info/RECORD
