Metadata-Version: 2.2
Name: phasic
Version: 0.22.22
Author-Email: Kasper Munch <kaspermunch@birc.au.dk>
Maintainer-Email: Kasper Munch <kaspermunch@birc.au.dk>
License: Copyright (c) 2025 Kasper Munch
Classifier: Development Status :: 4 - Beta
Classifier: Intended Audience :: Education
Classifier: Topic :: Software Development :: Build Tools
Classifier: License :: OSI Approved :: MIT License
Classifier: Programming Language :: Python :: 3
Classifier: Programming Language :: Python :: 3.9
Classifier: Programming Language :: Python :: 3.10
Classifier: Programming Language :: Python :: 3.11
Classifier: Programming Language :: Python :: 3.12
Classifier: Programming Language :: Python :: 3.13
Project-URL: Homepage, https://munch-group.org/phasic
Project-URL: Documentation, https://munch-group.org/phasic
Project-URL: Repository, https://github.com/munch-group/phasic.git
Project-URL: Issues, https://github.com/munch-group/phasic/issues
Requires-Python: >=3.9
Requires-Dist: pybind11>=2.10.0
Requires-Dist: jax
Requires-Dist: numpy
Requires-Dist: eigen
Requires-Dist: ipython
Requires-Dist: ipykernel
Requires-Dist: ipywidgets
Requires-Dist: json5
Requires-Dist: requests
Requires-Dist: graphviz
Requires-Dist: nlohmann_json
Requires-Dist: seaborn
Requires-Dist: pyyaml
Requires-Dist: psutil
Requires-Dist: rich
Requires-Dist: tqdm
Requires-Dist: multiprocess>=0.70.0
Provides-Extra: jax
Requires-Dist: jax>=0.4.0; extra == "jax"
Provides-Extra: ipfs
Requires-Dist: ipfshttpclient>=0.8.0; extra == "ipfs"
Requires-Dist: requests>=2.25.0; extra == "ipfs"
Provides-Extra: dev
Requires-Dist: pytest; extra == "dev"
Requires-Dist: tszip>=0.2.5; extra == "dev"
